{"columns": ["Image", "Split", "Height", "Width", "Unlabeled", "vessel", "vessel"], "columnsOptions": [null, {"subtitle": "folder name"}, {"postfix": "px"}, {"postfix": "px"}, {"subtitle": "area", "postfix": "%"}, {"subtitle": "objects count"}, {"subtitle": "covered area", "postfix": "%"}], "data": [["Image_01R.jpg", "ds0", 960, 999, 92.41, 1, 7.59], ["Image_02R.jpg", "ds0", 960, 999, 92.19, 1, 7.81], ["Image_08R.jpg", "ds0", 960, 999, 93.65, 1, 6.35], ["Image_07L.jpg", "ds0", 960, 999, 92.21, 1, 7.79], ["Image_01L.jpg", "ds0", 960, 999, 93.03, 1, 6.97], ["Image_04R.jpg", "ds0", 960, 999, 92.3, 1, 7.7], ["Image_12R.jpg", "ds0", 960, 999, 92.65, 1, 7.35], ["Image_11R.jpg", "ds0", 960, 999, 94.67, 1, 5.33], ["Image_06L.jpg", "ds0", 960, 999, 92.43, 1, 7.57], ["Image_03R.jpg", "ds0", 960, 999, 92.45, 1, 7.55], ["Image_13R.jpg", "ds0", 960, 999, 93.68, 1, 6.32], ["Image_06R.jpg", "ds0", 960, 999, 92.52, 1, 7.48], ["Image_09R.jpg", "ds0", 960, 999, 94.91, 1, 5.09], ["Image_03L.jpg", "ds0", 960, 999, 92.16, 1, 7.84], ["Image_12L.jpg", "ds0", 960, 999, 92.8, 1, 7.2], ["Image_05R.jpg", "ds0", 960, 999, 91.48, 1, 8.52], ["Image_14L.jpg", "ds0", 960, 999, 93.12, 1, 6.88], ["Image_14R.jpg", "ds0", 960, 999, 94.15, 1, 5.85], ["Image_10L.jpg", "ds0", 960, 999, 93.74, 1, 6.26], ["Image_02L.jpg", "ds0", 960, 999, 91.89, 1, 8.11], ["Image_09L.jpg", "ds0", 960, 999, 94.94, 1, 5.06], ["Image_11L.jpg", "ds0", 960, 999, 94.67, 1, 5.33], ["Image_08L.jpg", "ds0", 960, 999, 93.53, 1, 6.47], ["Image_10R.jpg", "ds0", 960, 999, 93.81, 1, 6.19], ["Image_13L.jpg", "ds0", 960, 999, 93.85, 1, 6.15], ["Image_07R.jpg", "ds0", 960, 999, 92.39, 1, 7.61], ["Image_04L.jpg", "ds0", 960, 999, 92.16, 1, 7.84], ["Image_05L.jpg", "ds0", 960, 999, 92.08, 1, 7.92]], "options": {"fixColumns": 1}, "referencesRow": [[884682], [884664], [884675], [884671], [884669], [884677], [884680], [884665], [884683], [884688], [884686], [884667], [884679], [884681], [884672], [884690], [884678], [884673], [884689], [884666], [884691], [884676], [884668], [884670], [884674], [884685], [884687], [884684]]}